{"name":"openssl","counts":{"unstable":10,"stable":53,"unmarked":306},"submodules":[{"name":"asn1","counts":{"unstable":0,"stable":1,"unmarked":6},"submodules":[]},{"name":"bio","counts":{"unstable":2,"stable":1,"unmarked":7},"submodules":[]},{"name":"bn","counts":{"unstable":0,"stable":9,"unmarked":56},"submodules":[{"name":"unchecked","counts":{"unstable":0,"stable":0,"unmarked":1},"submodules":[]}]},{"name":"crypto","counts":{"unstable":2,"stable":11,"unmarked":79},"submodules":[{"name":"hash","counts":{"unstable":1,"stable":3,"unmarked":17},"submodules":[]},{"name":"hmac","counts":{"unstable":1,"stable":2,"unmarked":6},"submodules":[]},{"name":"memcmp","counts":{"unstable":0,"stable":0,"unmarked":2},"submodules":[]},{"name":"pkcs5","counts":{"unstable":0,"stable":0,"unmarked":2},"submodules":[]},{"name":"pkey","counts":{"unstable":0,"stable":3,"unmarked":30},"submodules":[]},{"name":"rand","counts":{"unstable":0,"stable":0,"unmarked":2},"submodules":[]},{"name":"symm","counts":{"unstable":0,"stable":3,"unmarked":19},"submodules":[]}]},{"name":"ssl","counts":{"unstable":6,"stable":24,"unmarked":51},"submodules":[{"name":"error","counts":{"unstable":1,"stable":9,"unmarked":10},"submodules":[]}]},{"name":"x509","counts":{"unstable":0,"stable":7,"unmarked":106},"submodules":[]}]}